<keymap version="1" name="ReSharper copy" parent="ReSharper">
  <action id="CloseContent">
    <keyboard-shortcut first-keystroke="ctrl f4" />
    <keyboard-shortcut first-keystroke="ctrl w" />
  </action>
  <action id="Console.TableResult.NextPage" />
  <action id="Console.TableResult.PreviousPage" />
  <action id="EditorSelectWord" />
  <action id="FindNext">
    <keyboard-shortcut first-keystroke="f3" />
    <keyboard-shortcut first-keystroke="ctrl alt page_down" />
    <keyboard-shortcut first-keystroke="shift alt slash" />
  </action>
  <action id="GotoTypeDeclaration">
    <mouse-shortcut keystroke="shift control button1" />
  </action>
  <action id="MoveEditorToOppositeTabGroup">
    <keyboard-shortcut first-keystroke="shift ctrl m" />
  </action>
  <action id="MoveLineDown">
    <keyboard-shortcut first-keystroke="ctrl alt down" />
  </action>
  <action id="MoveLineUp">
    <keyboard-shortcut first-keystroke="ctrl alt up" />
  </action>
  <action id="MoveStatementDown" />
  <action id="MoveStatementUp" />
  <action id="NextOccurence" />
  <action id="NextSplitter">
    <keyboard-shortcut first-keystroke="ctrl alt right" />
  </action>
  <action id="OpenEditorInOppositeTabGroup">
    <keyboard-shortcut first-keystroke="shift ctrl o" />
  </action>
  <action id="PrevSplitter">
    <keyboard-shortcut first-keystroke="ctrl alt left" />
  </action>
  <action id="PreviousOccurence" />
  <action id="ReopenClosedTab">
    <keyboard-shortcut first-keystroke="shift ctrl t" />
  </action>
  <action id="RiderOpenSolution" />
  <action id="SmartSelect" />
  <action id="SplitHorizontally">
    <keyboard-shortcut first-keystroke="shift ctrl down" />
  </action>
  <action id="TableResult.GrowSelection" />
  <action id="UsageFiltering.WriteAccess" />
</keymap>